[
    {
        "type": 0,
        "location": [
            44,
            83
        ],
        "bgloc": [
            45,
            57
        ],
        "mean": [
            [
                43.23037040816326
            ]
        ],
        "min": [
            [
                5
            ]
        ],
        "max": [
            [
                83
            ]
        ],
        "RawIntDen": [
            [
                4236
            ]
        ],
        "IntDen": [
            [
                42.36576300000001
            ]
        ],
        "local_bg": [
            [
                2.907872448979592
            ]
        ],
        "area": [
            0.9800000000000002
        ],
        "distance": 0.05902995919424479,
        "points": [
            [
                44.0,
                89.8
            ],
            [
                38.4,
                88.6
            ],
            [
                35.8,
                83.0
            ],
            [
                40.6,
                79.6
            ],
            [
                44.0,
                78.8
            ],
            [
                47.0,
                80.0
            ],
            [
                47.4,
                83.0
            ],
            [
                48.8,
                87.8
            ]
        ],
        "shift": null,
        "channel": 0,
        "closest_Dend": 0
    },
    {
        "type": 0,
        "location": [
            74,
            125
        ],
        "bgloc": [
            74,
            181
        ],
        "mean": [
            [
                13.891467857142857
            ]
        ],
        "min": [
            [
                0
            ]
        ],
        "max": [
            [
                39
            ]
        ],
        "RawIntDen": [
            [
                777
            ]
        ],
        "IntDen": [
            [
                7.779222000000002
            ]
        ],
        "local_bg": [
            [
                0.01785535714285714
            ]
        ],
        "area": [
            0.56
        ],
        "distance": 3.002271554554524,
        "points": [
            [
                74.0,
                130.0
            ],
            [
                71.2,
                127.8
            ],
            [
                70.2,
                125.0
            ],
            [
                71.0,
                122.0
            ],
            [
                74.0,
                120.2
            ],
            [
                77.0,
                122.0
            ],
            [
                78.0,
                125.0
            ],
            [
                77.0,
                128.0
            ]
        ],
        "shift": null,
        "channel": 0,
        "closest_Dend": 0
    },
    {
        "type": 0,
        "location": [
            77,
            114
        ],
        "bgloc": [
            77,
            148
        ],
        "mean": [
            [
                24.612923076923078
            ]
        ],
        "min": [
            [
                2
            ]
        ],
        "max": [
            [
                59
            ]
        ],
        "RawIntDen": [
            [
                1599
            ]
        ],
        "IntDen": [
            [
                15.998400000000004
            ]
        ],
        "local_bg": [
            [
                0.13844769230769227
            ]
        ],
        "area": [
            0.6500000000000001
        ],
        "distance": 3.3022715545545243,
        "points": [
            [
                77.0,
                118.6
            ],
            [
                74.0,
                117.0
            ],
            [
                73.6,
                114.0
            ],
            [
                74.0,
                111.0
            ],
            [
                77.0,
                110.0
            ],
            [
                82.8,
                108.2
            ],
            [
                81.2,
                114.0
            ],
            [
                80.0,
                117.0
            ]
        ],
        "shift": null,
        "channel": 0,
        "closest_Dend": 0
    },
    {
        "type": 0,
        "location": [
            90,
            109
        ],
        "bgloc": [
            85,
            128
        ],
        "mean": [
            [
                82.6982
            ]
        ],
        "min": [
            [
                12
            ]
        ],
        "max": [
            [
                164
            ]
        ],
        "RawIntDen": [
            [
                7112
            ]
        ],
        "IntDen": [
            [
                71.12045200000001
            ]
        ],
        "local_bg": [
            [
                0.7092313953488372
            ]
        ],
        "area": [
            0.8600000000000002
        ],
        "distance": 4.863087573372915,
        "points": [
            [
                90.0,
                112.6
            ],
            [
                87.0,
                112.0
            ],
            [
                85.6,
                109.0
            ],
            [
                83.8,
                102.8
            ],
            [
                90.0,
                103.4
            ],
            [
                94.6,
                104.4
            ],
            [
                96.0,
                109.0
            ],
            [
                93.0,
                112.0
            ]
        ],
        "shift": null,
        "channel": 0,
        "closest_Dend": 0
    },
    {
        "type": 0,
        "location": [
            106,
            120
        ],
        "bgloc": [
            101,
            155
        ],
        "mean": [
            [
                38.29849534883721
            ]
        ],
        "min": [
            [
                5
            ]
        ],
        "max": [
            [
                80
            ]
        ],
        "RawIntDen": [
            [
                3293
            ]
        ],
        "IntDen": [
            [
                32.93670600000001
            ]
        ],
        "local_bg": [
            [
                0.05813372093023255
            ]
        ],
        "area": [
            0.8600000000000002
        ],
        "distance": 6.47244783289371,
        "points": [
            [
                106.0,
                125.0
            ],
            [
                103.4,
                122.6
            ],
            [
                102.6,
                120.0
            ],
            [
                102.6,
                116.6
            ],
            [
                106.0,
                115.0
            ],
            [
                110.4,
                115.6
            ],
            [
                112.6,
                120.0
            ],
            [
                111.4,
                125.4
            ]
        ],
        "shift": null,
        "channel": 0,
        "closest_Dend": 0
    },
    {
        "type": 0,
        "location": [
            112,
            93
        ],
        "bgloc": [
            114,
            74
        ],
        "mean": [
            [
                15.6651
            ]
        ],
        "min": [
            [
                0
            ]
        ],
        "max": [
            [
                67
            ]
        ],
        "RawIntDen": [
            [
                798
            ]
        ],
        "IntDen": [
            [
                7.989201000000002
            ]
        ],
        "local_bg": [
            [
                1.8037411764705884
            ]
        ],
        "area": [
            0.5100000000000001
        ],
        "distance": 6.732920775531048,
        "points": [
            [
                112.0,
                97.4
            ],
            [
                108.6,
                96.4
            ],
            [
                107.4,
                93.0
            ],
            [
                109.2,
                90.2
            ],
            [
                112.0,
                89.4
            ],
            [
                114.8,
                90.2
            ],
            [
                115.4,
                93.0
            ],
            [
                115.6,
                96.6
            ]
        ],
        "shift": null,
        "channel": 0,
        "closest_Dend": 0
    },
    {
        "type": 0,
        "location": [
            119,
            125
        ],
        "bgloc": [
            114,
            167
        ],
        "mean": [
            [
                13.152530769230768
            ]
        ],
        "min": [
            [
                1
            ]
        ],
        "max": [
            [
                32
            ]
        ],
        "RawIntDen": [
            [
                683
            ]
        ],
        "IntDen": [
            [
                6.839316000000001
            ]
        ],
        "local_bg": [
            [
                11.095044230769231
            ]
        ],
        "area": [
            0.5200000000000001
        ],
        "distance": 7.795141724368467,
        "points": [
            [
                119.0,
                129.0
            ],
            [
                116.0,
                128.0
            ],
            [
                114.0,
                125.0
            ],
            [
                115.6,
                121.6
            ],
            [
                119.0,
                121.2
            ],
            [
                121.4,
                122.6
            ],
            [
                122.8,
                125.0
            ],
            [
                122.0,
                128.0
            ]
        ],
        "shift": null,
        "channel": 0,
        "closest_Dend": 0
    },
    {
        "type": 0,
        "location": [
            122,
            121
        ],
        "bgloc": [
            118,
            155
        ],
        "mean": [
            [
                27.952561333333335
            ]
        ],
        "min": [
            [
                2
            ]
        ],
        "max": [
            [
                96
            ]
        ],
        "RawIntDen": [
            [
                2096
            ]
        ],
        "IntDen": [
            [
                20.964421000000005
            ]
        ],
        "local_bg": [
            [
                1.413192
            ]
        ],
        "area": [
            0.7500000000000001
        ],
        "distance": 8.049134234340613,
        "points": [
            [
                122.0,
                124.4
            ],
            [
                119.6,
                123.4
            ],
            [
                118.0,
                121.0
            ],
            [
                119.0,
                118.0
            ],
            [
                122.0,
                113.6
            ],
            [
                127.0,
                116.0
            ],
            [
                128.4,
                121.0
            ],
            [
                124.8,
                123.8
            ]
        ],
        "shift": null,
        "channel": 0,
        "closest_Dend": 0
    },
    {
        "type": 0,
        "location": [
            132,
            96
        ],
        "bgloc": [
            132,
            79
        ],
        "mean": [
            [
                37.80257230769231
            ]
        ],
        "min": [
            [
                7
            ]
        ],
        "max": [
            [
                84
            ]
        ],
        "RawIntDen": [
            [
                2457
            ]
        ],
        "IntDen": [
            [
                24.571672000000003
            ]
        ],
        "local_bg": [
            [
                0.36919384615384615
            ]
        ],
        "area": [
            0.6500000000000001
        ],
        "distance": 8.81181926792692,
        "points": [
            [
                132.0,
                100.4
            ],
            [
                128.6,
                99.4
            ],
            [
                126.6,
                96.0
            ],
            [
                128.8,
                92.8
            ],
            [
                132.0,
                92.8
            ],
            [
                135.8,
                92.2
            ],
            [
                137.2,
                96.0
            ],
            [
                135.4,
                99.4
            ]
        ],
        "shift": null,
        "channel": 0,
        "closest_Dend": 0
    },
    {
        "type": 0,
        "location": [
            141,
            116
        ],
        "bgloc": [
            139,
            137
        ],
        "mean": [
            [
                43.28980240963855
            ]
        ],
        "min": [
            [
                6
            ]
        ],
        "max": [
            [
                91
            ]
        ],
        "RawIntDen": [
            [
                3593
            ]
        ],
        "IntDen": [
            [
                35.930536
            ]
        ],
        "local_bg": [
            [
                31.659484337349394
            ]
        ],
        "area": [
            0.8300000000000002
        ],
        "distance": 9.827710247687357,
        "points": [
            [
                141.0,
                120.2
            ],
            [
                138.0,
                119.0
            ],
            [
                133.4,
                116.0
            ],
            [
                137.2,
                112.2
            ],
            [
                141.0,
                110.2
            ],
            [
                144.6,
                112.4
            ],
            [
                147.4,
                116.0
            ],
            [
                144.2,
                119.2
            ]
        ],
        "shift": null,
        "channel": 0,
        "closest_Dend": 0
    },
    {
        "type": 0,
        "location": [
            155,
            98
        ],
        "bgloc": [
            155,
            84
        ],
        "mean": [
            [
                39.90106833333333
            ]
        ],
        "min": [
            [
                2
            ]
        ],
        "max": [
            [
                135
            ]
        ],
        "RawIntDen": [
            [
                2394
            ]
        ],
        "IntDen": [
            [
                23.940641
            ]
        ],
        "local_bg": [
            [
                0.416625
            ]
        ],
        "area": [
            0.6000000000000001
        ],
        "distance": 11.16311602354074,
        "points": [
            [
                155.0,
                102.2
            ],
            [
                151.0,
                102.0
            ],
            [
                150.6,
                98.0
            ],
            [
                152.0,
                95.0
            ],
            [
                155.0,
                94.8
            ],
            [
                158.0,
                95.0
            ],
            [
                159.4,
                98.0
            ],
            [
                158.4,
                101.4
            ]
        ],
        "shift": null,
        "channel": 0,
        "closest_Dend": 0
    },
    {
        "type": 0,
        "location": [
            158,
            124
        ],
        "bgloc": [
            158,
            162
        ],
        "mean": [
            [
                13.318668
            ]
        ],
        "min": [
            [
                0
            ]
        ],
        "max": [
            [
                44
            ]
        ],
        "RawIntDen": [
            [
                665
            ]
        ],
        "IntDen": [
            [
                6.659334000000001
            ]
        ],
        "local_bg": [
            [
                0.159984
            ]
        ],
        "area": [
            0.5000000000000001
        ],
        "distance": 11.463116023540739,
        "points": [
            [
                158.0,
                128.0
            ],
            [
                155.0,
                127.0
            ],
            [
                154.0,
                124.0
            ],
            [
                155.0,
                121.0
            ],
            [
                158.0,
                120.2
            ],
            [
                161.0,
                121.0
            ],
            [
                161.8,
                124.0
            ],
            [
                160.8,
                126.8
            ]
        ],
        "shift": null,
        "channel": 0,
        "closest_Dend": 0
    },
    {
        "type": 0,
        "location": [
            158,
            116
        ],
        "bgloc": [
            158,
            138
        ],
        "mean": [
            [
                18.32544
            ]
        ],
        "min": [
            [
                2
            ]
        ],
        "max": [
            [
                64
            ]
        ],
        "RawIntDen": [
            [
                1007
            ]
        ],
        "IntDen": [
            [
                10.078992000000001
            ]
        ],
        "local_bg": [
            [
                0.7817399999999999
            ]
        ],
        "area": [
            0.5500000000000002
        ],
        "distance": 11.463116023540739,
        "points": [
            [
                158.0,
                120.6
            ],
            [
                155.2,
                118.8
            ],
            [
                154.2,
                116.0
            ],
            [
                154.4,
                112.4
            ],
            [
                158.0,
                110.6
            ],
            [
                161.0,
                113.0
            ],
            [
                161.6,
                116.0
            ],
            [
                161.4,
                119.4
            ]
        ],
        "shift": null,
        "channel": 0,
        "closest_Dend": 0
    },
    {
        "type": 0,
        "location": [
            180,
            117
        ],
        "bgloc": [
            181,
            142
        ],
        "mean": [
            [
                46.86701126760563
            ]
        ],
        "min": [
            [
                12
            ]
        ],
        "max": [
            [
                95
            ]
        ],
        "RawIntDen": [
            [
                3327
            ]
        ],
        "IntDen": [
            [
                33.27557800000001
            ]
        ],
        "local_bg": [
            [
                0.014083098591549294
            ]
        ],
        "area": [
            0.7100000000000002
        ],
        "distance": 13.614035719732597,
        "points": [
            [
                180.0,
                121.8
            ],
            [
                175.6,
                121.4
            ],
            [
                175.2,
                117.0
            ],
            [
                177.0,
                114.0
            ],
            [
                180.0,
                112.4
            ],
            [
                184.8,
                112.2
            ],
            [
                184.8,
                117.0
            ],
            [
                183.2,
                120.2
            ]
        ],
        "shift": null,
        "channel": 0,
        "closest_Dend": 0
    },
    {
        "type": 0,
        "location": [
            197,
            110
        ],
        "bgloc": [
            197,
            122
        ],
        "mean": [
            [
                34.99435490196078
            ]
        ],
        "min": [
            [
                3
            ]
        ],
        "max": [
            [
                110
            ]
        ],
        "RawIntDen": [
            [
                1784
            ]
        ],
        "IntDen": [
            [
                17.847121
            ]
        ],
        "local_bg": [
            [
                0.9802941176470586
            ]
        ],
        "area": [
            0.5100000000000001
        ],
        "distance": 15.340654976403847,
        "points": [
            [
                197.0,
                114.0
            ],
            [
                194.0,
                113.0
            ],
            [
                192.8,
                110.0
            ],
            [
                193.6,
                106.6
            ],
            [
                197.0,
                106.2
            ],
            [
                200.8,
                106.2
            ],
            [
                200.2,
                110.0
            ],
            [
                200.0,
                113.0
            ]
        ],
        "shift": null,
        "channel": 0,
        "closest_Dend": 0
    },
    {
        "type": 0,
        "location": [
            202,
            95
        ],
        "bgloc": [
            201,
            77
        ],
        "mean": [
            [
                52.31325303030303
            ]
        ],
        "min": [
            [
                4
            ]
        ],
        "max": [
            [
                117
            ]
        ],
        "RawIntDen": [
            [
                3452
            ]
        ],
        "IntDen": [
            [
                34.52674700000001
            ]
        ],
        "local_bg": [
            [
                0.15149999999999997
            ]
        ],
        "area": [
            0.6600000000000001
        ],
        "distance": 15.900207513288052,
        "points": [
            [
                202.0,
                99.8
            ],
            [
                197.6,
                99.4
            ],
            [
                197.6,
                95.0
            ],
            [
                199.0,
                92.0
            ],
            [
                202.0,
                91.6
            ],
            [
                205.0,
                92.0
            ],
            [
                206.4,
                95.0
            ],
            [
                206.4,
                99.4
            ]
        ],
        "shift": null,
        "channel": 0,
        "closest_Dend": 0
    },
    {
        "type": 0,
        "location": [
            214,
            112
        ],
        "bgloc": [
            214,
            129
        ],
        "mean": [
            [
                29.076457142857144
            ]
        ],
        "min": [
            [
                3
            ]
        ],
        "max": [
            [
                79
            ]
        ],
        "RawIntDen": [
            [
                1831
            ]
        ],
        "IntDen": [
            [
                18.318168000000004
            ]
        ],
        "local_bg": [
            [
                0.19045714285714285
            ]
        ],
        "area": [
            0.6300000000000001
        ],
        "distance": 17.031302998561113,
        "points": [
            [
                214.0,
                116.0
            ],
            [
                210.8,
                115.2
            ],
            [
                208.8,
                112.0
            ],
            [
                211.4,
                109.4
            ],
            [
                214.0,
                108.2
            ],
            [
                218.4,
                107.6
            ],
            [
                219.4,
                112.0
            ],
            [
                217.2,
                115.2
            ]
        ],
        "shift": null,
        "channel": 0,
        "closest_Dend": 0
    },
    {
        "type": 0,
        "location": [
            216,
            97
        ],
        "bgloc": [
            216,
            85
        ],
        "mean": [
            [
                41.33856470588235
            ]
        ],
        "min": [
            [
                4
            ]
        ],
        "max": [
            [
                132
            ]
        ],
        "RawIntDen": [
            [
                2811
            ]
        ],
        "IntDen": [
            [
                28.110224000000002
            ]
        ],
        "local_bg": [
            [
                17.89526911764706
            ]
        ],
        "area": [
            0.6800000000000002
        ],
        "distance": 17.26711442481946,
        "points": [
            [
                216.0,
                101.8
            ],
            [
                211.4,
                101.6
            ],
            [
                211.6,
                97.0
            ],
            [
                212.4,
                93.4
            ],
            [
                216.0,
                93.0
            ],
            [
                219.0,
                94.0
            ],
            [
                220.2,
                97.0
            ],
            [
                220.4,
                101.4
            ]
        ],
        "shift": null,
        "channel": 0,
        "closest_Dend": 0
    },
    {
        "type": 0,
        "location": [
            226,
            112
        ],
        "bgloc": [
            226,
            130
        ],
        "mean": [
            [
                32.11359253731344
            ]
        ],
        "min": [
            [
                1
            ]
        ],
        "max": [
            [
                106
            ]
        ],
        "RawIntDen": [
            [
                2151
            ]
        ],
        "IntDen": [
            [
                21.516107000000005
            ]
        ],
        "local_bg": [
            [
                0.14923880597014924
            ]
        ],
        "area": [
            0.6700000000000002
        ],
        "distance": 18.26711442481946,
        "points": [
            [
                226.0,
                115.2
            ],
            [
                223.2,
                114.8
            ],
            [
                221.8,
                112.0
            ],
            [
                221.6,
                107.6
            ],
            [
                226.0,
                106.8
            ],
            [
                230.0,
                108.0
            ],
            [
                230.8,
                112.0
            ],
            [
                229.0,
                115.0
            ]
        ],
        "shift": null,
        "channel": 0,
        "closest_Dend": 0
    },
    {
        "type": 0,
        "location": [
            243,
            116
        ],
        "bgloc": [
            246,
            142
        ],
        "mean": [
            [
                17.704895999999998
            ]
        ],
        "min": [
            [
                1
            ]
        ],
        "max": [
            [
                42
            ]
        ],
        "RawIntDen": [
            [
                1327
            ]
        ],
        "IntDen": [
            [
                13.278672000000002
            ]
        ],
        "local_bg": [
            [
                0.319968
            ]
        ],
        "area": [
            0.7500000000000001
        ],
        "distance": 19.78125656044319,
        "points": [
            [
                243.0,
                122.2
            ],
            [
                239.6,
                119.4
            ],
            [
                237.4,
                116.0
            ],
            [
                239.4,
                112.4
            ],
            [
                243.0,
                112.2
            ],
            [
                246.0,
                113.0
            ],
            [
                248.4,
                116.0
            ],
            [
                247.4,
                120.4
            ]
        ],
        "shift": null,
        "channel": 0,
        "closest_Dend": 0
    },
    {
        "type": 0,
        "location": [
            243,
            132
        ],
        "bgloc": [
            251,
            189
        ],
        "mean": [
            [
                45.57989672131148
            ]
        ],
        "min": [
            [
                6
            ]
        ],
        "max": [
            [
                98
            ]
        ],
        "RawIntDen": [
            [
                2780
            ]
        ],
        "IntDen": [
            [
                27.803737000000005
            ]
        ],
        "local_bg": [
            [
                0.0
            ]
        ],
        "area": [
            0.6100000000000001
        ],
        "distance": 19.97924645917542,
        "points": [
            [
                243.0,
                136.8
            ],
            [
                239.4,
                135.6
            ],
            [
                238.2,
                132.0
            ],
            [
                240.0,
                129.0
            ],
            [
                243.0,
                127.8
            ],
            [
                246.0,
                129.0
            ],
            [
                247.6,
                132.0
            ],
            [
                246.0,
                135.0
            ]
        ],
        "shift": null,
        "channel": 0,
        "closest_Dend": 0
    },
    {
        "type": 0,
        "location": [
            257,
            93
        ],
        "bgloc": [
            255,
            77
        ],
        "mean": [
            [
                23.050326315789473
            ]
        ],
        "min": [
            [
                2
            ]
        ],
        "max": [
            [
                51
            ]
        ],
        "RawIntDen": [
            [
                1313
            ]
        ],
        "IntDen": [
            [
                13.138686000000003
            ]
        ],
        "local_bg": [
            [
                0.21050526315789472
            ]
        ],
        "area": [
            0.5700000000000001
        ],
        "distance": 21.468104940679627,
        "points": [
            [
                257.0,
                96.6
            ],
            [
                253.6,
                96.4
            ],
            [
                251.4,
                93.0
            ],
            [
                254.0,
                90.0
            ],
            [
                257.0,
                89.8
            ],
            [
                259.8,
                90.2
            ],
            [
                261.8,
                93.0
            ],
            [
                260.8,
                96.8
            ]
        ],
        "shift": null,
        "channel": 0,
        "closest_Dend": 0
    },
    {
        "type": 0,
        "location": [
            269,
            93
        ],
        "bgloc": [
            269,
            79
        ],
        "mean": [
            [
                26.69087903225806
            ]
        ],
        "min": [
            [
                1
            ]
        ],
        "max": [
            [
                79
            ]
        ],
        "RawIntDen": [
            [
                1654
            ]
        ],
        "IntDen": [
            [
                16.548345
            ]
        ],
        "local_bg": [
            [
                0.1935290322580645
            ]
        ],
        "area": [
            0.6200000000000001
        ],
        "distance": 22.58529823363349,
        "points": [
            [
                269.0,
                97.2
            ],
            [
                265.2,
                96.8
            ],
            [
                264.0,
                93.0
            ],
            [
                266.2,
                90.2
            ],
            [
                269.0,
                90.0
            ],
            [
                272.0,
                90.0
            ],
            [
                273.4,
                93.0
            ],
            [
                273.2,
                97.2
            ]
        ],
        "shift": null,
        "channel": 0,
        "closest_Dend": 0
    },
    {
        "type": 0,
        "location": [
            285,
            107
        ],
        "bgloc": [
            285,
            122
        ],
        "mean": [
            [
                53.3948302631579
            ]
        ],
        "min": [
            [
                14
            ]
        ],
        "max": [
            [
                84
            ]
        ],
        "RawIntDen": [
            [
                4058
            ]
        ],
        "IntDen": [
            [
                40.58007100000001
            ]
        ],
        "local_bg": [
            [
                22.48459342105263
            ]
        ],
        "area": [
            0.7600000000000001
        ],
        "distance": 24.14229462875996,
        "points": [
            [
                285.0,
                112.2
            ],
            [
                280.6,
                111.4
            ],
            [
                280.8,
                107.0
            ],
            [
                281.0,
                103.0
            ],
            [
                285.0,
                102.8
            ],
            [
                289.8,
                102.2
            ],
            [
                288.6,
                107.0
            ],
            [
                288.6,
                110.6
            ]
        ],
        "shift": null,
        "channel": 0,
        "closest_Dend": 0
    },
    {
        "type": 0,
        "location": [
            287,
            91
        ],
        "bgloc": [
            283,
            74
        ],
        "mean": [
            [
                23.578287096774194
            ]
        ],
        "min": [
            [
                2
            ]
        ],
        "max": [
            [
                69
            ]
        ],
        "RawIntDen": [
            [
                1461
            ]
        ],
        "IntDen": [
            [
                14.618538000000004
            ]
        ],
        "local_bg": [
            [
                0.06450967741935483
            ]
        ],
        "area": [
            0.6200000000000001
        ],
        "distance": 25.023576232391953,
        "points": [
            [
                287.0,
                95.8
            ],
            [
                283.0,
                95.0
            ],
            [
                283.0,
                91.0
            ],
            [
                284.0,
                88.0
            ],
            [
                287.0,
                87.0
            ],
            [
                290.0,
                88.0
            ],
            [
                290.8,
                91.0
            ],
            [
                290.8,
                94.8
            ]
        ],
        "shift": null,
        "channel": 0,
        "closest_Dend": 0
    },
    {
        "type": 0,
        "location": [
            320,
            100
        ],
        "bgloc": [
            326,
            119
        ],
        "mean": [
            [
                21.220100000000002
            ]
        ],
        "min": [
            [
                5
            ]
        ],
        "max": [
            [
                51
            ]
        ],
        "RawIntDen": [
            [
                1145
            ]
        ],
        "IntDen": [
            [
                11.458854000000004
            ]
        ],
        "local_bg": [
            [
                24.571616666666667
            ]
        ],
        "area": [
            0.5400000000000001
        ],
        "distance": 27.521179693447852,
        "points": [
            [
                320.0,
                104.6
            ],
            [
                317.0,
                103.0
            ],
            [
                315.4,
                100.0
            ],
            [
                317.2,
                97.2
            ],
            [
                320.0,
                96.2
            ],
            [
                323.0,
                97.0
            ],
            [
                324.4,
                100.0
            ],
            [
                323.0,
                103.0
            ]
        ],
        "shift": null,
        "channel": 0,
        "closest_Dend": 0
    },
    {
        "type": 0,
        "location": [
            326,
            97
        ],
        "bgloc": [
            331,
            114
        ],
        "mean": [
            [
                10.926179999999999
            ]
        ],
        "min": [
            [
                2
            ]
        ],
        "max": [
            [
                25
            ]
        ],
        "RawIntDen": [
            [
                600
            ]
        ],
        "IntDen": [
            [
                6.009399000000001
            ]
        ],
        "local_bg": [
            [
                32.869440000000004
            ]
        ],
        "area": [
            0.5500000000000002
        ],
        "distance": 28.18525800208321,
        "points": [
            [
                326.0,
                102.0
            ],
            [
                323.0,
                100.0
            ],
            [
                321.6,
                97.0
            ],
            [
                322.2,
                93.2
            ],
            [
                326.0,
                93.6
            ],
            [
                329.0,
                94.0
            ],
            [
                329.8,
                97.0
            ],
            [
                328.8,
                99.8
            ]
        ],
        "shift": null,
        "channel": 0,
        "closest_Dend": 0
    },
    {
        "type": 0,
        "location": [
            328,
            81
        ],
        "bgloc": [
            324,
            72
        ],
        "mean": [
            [
                58.732159016393446
            ]
        ],
        "min": [
            [
                5
            ]
        ],
        "max": [
            [
                121
            ]
        ],
        "RawIntDen": [
            [
                3582
            ]
        ],
        "IntDen": [
            [
                35.826617000000006
            ]
        ],
        "local_bg": [
            [
                1.0818590163934425
            ]
        ],
        "area": [
            0.6100000000000001
        ],
        "distance": 28.940111738199576,
        "points": [
            [
                328.0,
                86.8
            ],
            [
                323.6,
                85.4
            ],
            [
                324.6,
                81.0
            ],
            [
                325.4,
                78.4
            ],
            [
                328.0,
                78.2
            ],
            [
                330.2,
                78.8
            ],
            [
                333.4,
                81.0
            ],
            [
                332.4,
                85.4
            ]
        ],
        "shift": null,
        "channel": 0,
        "closest_Dend": 0
    },
    {
        "type": 0,
        "location": [
            335,
            93
        ],
        "bgloc": [
            342,
            109
        ],
        "mean": [
            [
                15.267703846153847
            ]
        ],
        "min": [
            [
                2
            ]
        ],
        "max": [
            [
                38
            ]
        ],
        "RawIntDen": [
            [
                793
            ]
        ],
        "IntDen": [
            [
                7.939206000000002
            ]
        ],
        "local_bg": [
            [
                3.038157692307692
            ]
        ],
        "area": [
            0.5200000000000001
        ],
        "distance": 29.062528386144415,
        "points": [
            [
                335.0,
                98.2
            ],
            [
                332.0,
                96.0
            ],
            [
                330.4,
                93.0
            ],
            [
                331.2,
                89.2
            ],
            [
                335.0,
                90.0
            ],
            [
                337.4,
                90.6
            ],
            [
                338.2,
                93.0
            ],
            [
                338.0,
                96.0
            ]
        ],
        "shift": null,
        "channel": 0,
        "closest_Dend": 0
    },
    {
        "type": 0,
        "location": [
            353,
            86
        ],
        "bgloc": [
            368,
            105
        ],
        "mean": [
            [
                19.918406153846156
            ]
        ],
        "min": [
            [
                2
            ]
        ],
        "max": [
            [
                87
            ]
        ],
        "RawIntDen": [
            [
                1294
            ]
        ],
        "IntDen": [
            [
                12.946964000000005
            ]
        ],
        "local_bg": [
            [
                0.6768553846153845
            ]
        ],
        "area": [
            0.6500000000000001
        ],
        "distance": 30.721181297492837,
        "points": [
            [
                353.0,
                90.8
            ],
            [
                350.0,
                89.0
            ],
            [
                348.8,
                86.0
            ],
            [
                348.6,
                81.6
            ],
            [
                353.0,
                82.6
            ],
            [
                357.4,
                81.6
            ],
            [
                357.6,
                86.0
            ],
            [
                356.4,
                89.4
            ]
        ],
        "shift": null,
        "channel": 0,
        "closest_Dend": 0
    },
    {
        "type": 0,
        "location": [
            350,
            67
        ],
        "bgloc": [
            344,
            58
        ],
        "mean": [
            [
                48.855130136986304
            ]
        ],
        "min": [
            [
                3
            ]
        ],
        "max": [
            [
                105
            ]
        ],
        "RawIntDen": [
            [
                3566
            ]
        ],
        "IntDen": [
            [
                35.66424500000001
            ]
        ],
        "local_bg": [
            [
                1.0135972602739725
            ]
        ],
        "area": [
            0.7300000000000001
        ],
        "distance": 31.647875941267017,
        "points": [
            [
                350.0,
                74.4
            ],
            [
                347.4,
                69.6
            ],
            [
                346.8,
                67.0
            ],
            [
                347.4,
                64.4
            ],
            [
                350.0,
                63.2
            ],
            [
                352.4,
                64.6
            ],
            [
                356.8,
                67.0
            ],
            [
                355.4,
                72.4
            ]
        ],
        "shift": null,
        "channel": 0,
        "closest_Dend": 0
    },
    {
        "type": 0,
        "location": [
            358,
            52
        ],
        "bgloc": [
            344,
            38
        ],
        "mean": [
            [
                18.85857906976744
            ]
        ],
        "min": [
            [
                1
            ]
        ],
        "max": [
            [
                53
            ]
        ],
        "RawIntDen": [
            [
                810
            ]
        ],
        "IntDen": [
            [
                8.109189000000002
            ]
        ],
        "local_bg": [
            [
                0.023253488372093022
            ]
        ],
        "area": [
            0.4300000000000001
        ],
        "distance": 33.356556979989115,
        "points": [
            [
                358.0,
                57.4
            ],
            [
                355.0,
                55.0
            ],
            [
                354.8,
                52.0
            ],
            [
                355.4,
                49.4
            ],
            [
                358.0,
                48.8
            ],
            [
                360.4,
                49.6
            ],
            [
                361.4,
                52.0
            ],
            [
                361.0,
                55.0
            ]
        ],
        "shift": null,
        "channel": 0,
        "closest_Dend": 0
    },
    {
        "type": 0,
        "location": [
            373,
            64
        ],
        "bgloc": [
            386,
            77
        ],
        "mean": [
            [
                15.875335384615385
            ]
        ],
        "min": [
            [
                3
            ]
        ],
        "max": [
            [
                55
            ]
        ],
        "RawIntDen": [
            [
                1031
            ]
        ],
        "IntDen": [
            [
                10.318968000000002
            ]
        ],
        "local_bg": [
            [
                16.76755384615385
            ]
        ],
        "area": [
            0.6500000000000001
        ],
        "distance": 33.56868901434508,
        "points": [
            [
                373.0,
                68.8
            ],
            [
                370.0,
                67.0
            ],
            [
                369.6,
                64.0
            ],
            [
                369.4,
                60.4
            ],
            [
                373.0,
                58.0
            ],
            [
                376.0,
                61.0
            ],
            [
                377.6,
                64.0
            ],
            [
                376.2,
                67.2
            ]
        ],
        "shift": null,
        "channel": 0,
        "closest_Dend": 0
    },
    {
        "type": 0,
        "location": [
            382,
            66
        ],
        "bgloc": [
            406,
            90
        ],
        "mean": [
            [
                29.609941935483867
            ]
        ],
        "min": [
            [
                3
            ]
        ],
        "max": [
            [
                74
            ]
        ],
        "RawIntDen": [
            [
                1835
            ]
        ],
        "IntDen": [
            [
                18.358164000000002
            ]
        ],
        "local_bg": [
            [
                4.386658064516129
            ]
        ],
        "area": [
            0.6200000000000001
        ],
        "distance": 34.06366376117566,
        "points": [
            [
                382.0,
                71.2
            ],
            [
                378.0,
                70.0
            ],
            [
                376.8,
                66.0
            ],
            [
                379.2,
                63.2
            ],
            [
                382.0,
                62.2
            ],
            [
                385.0,
                63.0
            ],
            [
                386.0,
                66.0
            ],
            [
                385.0,
                69.0
            ]
        ],
        "shift": null,
        "channel": 0,
        "closest_Dend": 0
    },
    {
        "type": 0,
        "location": [
            362,
            42
        ],
        "bgloc": [
            342,
            21
        ],
        "mean": [
            [
                19.84584130434782
            ]
        ],
        "min": [
            [
                1
            ]
        ],
        "max": [
            [
                56
            ]
        ],
        "RawIntDen": [
            [
                912
            ]
        ],
        "IntDen": [
            [
                9.129087
            ]
        ],
        "local_bg": [
            [
                0.0
            ]
        ],
        "area": [
            0.4600000000000001
        ],
        "distance": 34.31744489160234,
        "points": [
            [
                362.0,
                45.2
            ],
            [
                359.2,
                44.8
            ],
            [
                358.0,
                42.0
            ],
            [
                359.4,
                39.4
            ],
            [
                362.0,
                38.2
            ],
            [
                365.0,
                39.0
            ],
            [
                366.4,
                42.0
            ],
            [
                365.0,
                45.0
            ]
        ],
        "shift": null,
        "channel": 0,
        "closest_Dend": 0
    },
    {
        "type": 0,
        "location": [
            388,
            56
        ],
        "bgloc": [
            407,
            75
        ],
        "mean": [
            [
                20.3313
            ]
        ],
        "min": [
            [
                2
            ]
        ],
        "max": [
            [
                42
            ]
        ],
        "RawIntDen": [
            [
                1341
            ]
        ],
        "IntDen": [
            [
                13.418658000000002
            ]
        ],
        "local_bg": [
            [
                6.347849999999999
            ]
        ],
        "area": [
            0.6600000000000001
        ],
        "distance": 35.223507366817216,
        "points": [
            [
                388.0,
                60.0
            ],
            [
                385.0,
                59.0
            ],
            [
                380.6,
                56.0
            ],
            [
                384.6,
                52.6
            ],
            [
                388.0,
                51.2
            ],
            [
                391.0,
                53.0
            ],
            [
                392.4,
                56.0
            ],
            [
                391.0,
                59.0
            ]
        ],
        "shift": null,
        "channel": 0,
        "closest_Dend": 0
    },
    {
        "type": 0,
        "location": [
            402,
            55
        ],
        "bgloc": [
            434,
            87
        ],
        "mean": [
            [
                24.584842857142856
            ]
        ],
        "min": [
            [
                6
            ]
        ],
        "max": [
            [
                49
            ]
        ],
        "RawIntDen": [
            [
                1548
            ]
        ],
        "IntDen": [
            [
                15.488451000000003
            ]
        ],
        "local_bg": [
            [
                0.3491714285714285
            ]
        ],
        "area": [
            0.6300000000000001
        ],
        "distance": 37.38778709517105,
        "points": [
            [
                402.0,
                58.8
            ],
            [
                399.0,
                58.0
            ],
            [
                396.6,
                55.0
            ],
            [
                397.2,
                50.2
            ],
            [
                402.0,
                49.8
            ],
            [
                405.0,
                52.0
            ],
            [
                405.4,
                55.0
            ],
            [
                404.4,
                57.4
            ]
        ],
        "shift": null,
        "channel": 0,
        "closest_Dend": 0
    },
    {
        "type": 0,
        "location": [
            404,
            40
        ],
        "bgloc": [
            423,
            59
        ],
        "mean": [
            [
                21.046282258064515
            ]
        ],
        "min": [
            [
                2
            ]
        ],
        "max": [
            [
                53
            ]
        ],
        "RawIntDen": [
            [
                1304
            ]
        ],
        "IntDen": [
            [
                13.048695000000002
            ]
        ],
        "local_bg": [
            [
                0.0
            ]
        ],
        "area": [
            0.6200000000000001
        ],
        "distance": 37.4584977732897,
        "points": [
            [
                404.0,
                43.4
            ],
            [
                400.8,
                43.2
            ],
            [
                397.2,
                40.0
            ],
            [
                401.0,
                37.0
            ],
            [
                404.0,
                36.6
            ],
            [
                407.0,
                37.0
            ],
            [
                409.0,
                40.0
            ],
            [
                407.0,
                43.0
            ]
        ],
        "shift": null,
        "channel": 0,
        "closest_Dend": 0
    },
    {
        "type": 0,
        "location": [
            374,
            32
        ],
        "bgloc": [
            355,
            13
        ],
        "mean": [
            [
                27.497249999999994
            ]
        ],
        "min": [
            [
                2
            ]
        ],
        "max": [
            [
                64
            ]
        ],
        "RawIntDen": [
            [
                1649
            ]
        ],
        "IntDen": [
            [
                16.49835
            ]
        ],
        "local_bg": [
            [
                0.016665
            ]
        ],
        "area": [
            0.6000000000000001
        ],
        "distance": 37.74134048576432,
        "points": [
            [
                374.0,
                36.8
            ],
            [
                370.8,
                35.2
            ],
            [
                369.4,
                32.0
            ],
            [
                371.0,
                29.0
            ],
            [
                374.0,
                28.0
            ],
            [
                377.0,
                29.0
            ],
            [
                379.6,
                32.0
            ],
            [
                377.0,
                35.0
            ]
        ],
        "shift": null,
        "channel": 0,
        "closest_Dend": 0
    },
    {
        "type": 0,
        "location": [
            399,
            16
        ],
        "bgloc": [
            389,
            10
        ],
        "mean": [
            [
                13.7902875
            ]
        ],
        "min": [
            [
                1
            ]
        ],
        "max": [
            [
                60
            ]
        ],
        "RawIntDen": [
            [
                661
            ]
        ],
        "IntDen": [
            [
                6.619338000000002
            ]
        ],
        "local_bg": [
            [
                0.20831249999999998
            ]
        ],
        "area": [
            0.4800000000000001
        ],
        "distance": 38.84684411910494,
        "points": [
            [
                399.0,
                20.4
            ],
            [
                396.0,
                19.0
            ],
            [
                394.4,
                16.0
            ],
            [
                396.2,
                13.2
            ],
            [
                399.0,
                13.0
            ],
            [
                401.8,
                13.2
            ],
            [
                403.0,
                16.0
            ],
            [
                402.6,
                19.6
            ]
        ],
        "shift": null,
        "channel": 0,
        "closest_Dend": 0
    }
]