[
    {
        "type": 0,
        "location": [
            13,
            156
        ],
        "bgloc": [
            22,
            185
        ],
        "mean": [
            [
                42.69013218390804
            ]
        ],
        "min": [
            [
                14
            ]
        ],
        "max": [
            [
                85
            ]
        ],
        "RawIntDen": [
            [
                3714
            ]
        ],
        "IntDen": [
            [
                37.140415000000004
            ]
        ],
        "local_bg": [
            [
                11.944079310344828
            ]
        ],
        "area": [
            0.8700000000000002
        ],
        "distance": 0.22135943621178616,
        "points": [
            [
                13.0,
                161.4
            ],
            [
                9.0,
                160.0
            ],
            [
                7.2,
                156.0
            ],
            [
                8.6,
                151.6
            ],
            [
                13.0,
                149.6
            ],
            [
                16.0,
                153.0
            ],
            [
                18.6,
                156.0
            ],
            [
                16.2,
                159.2
            ]
        ],
        "shift": null,
        "channel": 0,
        "closest_Dend": 0
    },
    {
        "type": 0,
        "location": [
            17,
            127
        ],
        "bgloc": [
            11,
            104
        ],
        "mean": [
            [
                43.29853068181818
            ]
        ],
        "min": [
            [
                6
            ]
        ],
        "max": [
            [
                104
            ]
        ],
        "RawIntDen": [
            [
                3810
            ]
        ],
        "IntDen": [
            [
                38.102707
            ]
        ],
        "local_bg": [
            [
                0.5113125
            ]
        ],
        "area": [
            0.8800000000000001
        ],
        "distance": 1.4328230946535747,
        "points": [
            [
                17.0,
                132.8
            ],
            [
                12.4,
                131.6
            ],
            [
                12.2,
                127.0
            ],
            [
                11.6,
                121.6
            ],
            [
                17.0,
                122.4
            ],
            [
                20.0,
                124.0
            ],
            [
                21.0,
                127.0
            ],
            [
                21.6,
                131.6
            ]
        ],
        "shift": null,
        "channel": 0,
        "closest_Dend": 0
    },
    {
        "type": 0,
        "location": [
            31,
            148
        ],
        "bgloc": [
            37,
            172
        ],
        "mean": [
            [
                41.43289220779221
            ]
        ],
        "min": [
            [
                6
            ]
        ],
        "max": [
            [
                112
            ]
        ],
        "RawIntDen": [
            [
                3190
            ]
        ],
        "IntDen": [
            [
                31.903327000000004
            ]
        ],
        "local_bg": [
            [
                12.115671428571428
            ]
        ],
        "area": [
            0.7700000000000001
        ],
        "distance": 2.2816977822807405,
        "points": [
            [
                31.0,
                152.2
            ],
            [
                28.0,
                151.0
            ],
            [
                25.2,
                148.0
            ],
            [
                26.6,
                143.6
            ],
            [
                31.0,
                142.2
            ],
            [
                34.6,
                144.4
            ],
            [
                36.2,
                148.0
            ],
            [
                34.8,
                151.8
            ]
        ],
        "shift": null,
        "channel": 0,
        "closest_Dend": 0
    },
    {
        "type": 0,
        "location": [
            33,
            114
        ],
        "bgloc": [
            24,
            73
        ],
        "mean": [
            [
                35.5702131147541
            ]
        ],
        "min": [
            [
                3
            ]
        ],
        "max": [
            [
                68
            ]
        ],
        "RawIntDen": [
            [
                2169
            ]
        ],
        "IntDen": [
            [
                21.697830000000003
            ]
        ],
        "local_bg": [
            [
                0.03278360655737705
            ]
        ],
        "area": [
            0.6100000000000001
        ],
        "distance": 3.219887351195945,
        "points": [
            [
                33.0,
                120.2
            ],
            [
                30.0,
                117.0
            ],
            [
                30.0,
                114.0
            ],
            [
                29.6,
                110.6
            ],
            [
                33.0,
                109.6
            ],
            [
                35.6,
                111.4
            ],
            [
                36.8,
                114.0
            ],
            [
                37.0,
                118.0
            ]
        ],
        "shift": null,
        "channel": 0,
        "closest_Dend": 0
    },
    {
        "type": 0,
        "location": [
            64,
            113
        ],
        "bgloc": [
            57,
            82
        ],
        "mean": [
            [
                35.56540862068965
            ]
        ],
        "min": [
            [
                6
            ]
        ],
        "max": [
            [
                78
            ]
        ],
        "RawIntDen": [
            [
                2062
            ]
        ],
        "IntDen": [
            [
                20.627937000000003
            ]
        ],
        "local_bg": [
            [
                0.01723965517241379
            ]
        ],
        "area": [
            0.5800000000000001
        ],
        "distance": 6.264022465473913,
        "points": [
            [
                64.0,
                117.8
            ],
            [
                61.0,
                116.0
            ],
            [
                59.4,
                113.0
            ],
            [
                61.0,
                110.0
            ],
            [
                64.0,
                108.6
            ],
            [
                67.0,
                110.0
            ],
            [
                68.4,
                113.0
            ],
            [
                67.2,
                116.2
            ]
        ],
        "shift": null,
        "channel": 0,
        "closest_Dend": 0
    },
    {
        "type": 0,
        "location": [
            83,
            138
        ],
        "bgloc": [
            91,
            163
        ],
        "mean": [
            [
                16.904559374999998
            ]
        ],
        "min": [
            [
                2
            ]
        ],
        "max": [
            [
                71
            ]
        ],
        "RawIntDen": [
            [
                1081
            ]
        ],
        "IntDen": [
            [
                10.818918
            ]
        ],
        "local_bg": [
            [
                0.2655984375
            ]
        ],
        "area": [
            0.6400000000000001
        ],
        "distance": 7.474139715275554,
        "points": [
            [
                83.0,
                141.2
            ],
            [
                80.4,
                140.6
            ],
            [
                78.2,
                138.0
            ],
            [
                78.6,
                133.6
            ],
            [
                83.0,
                132.0
            ],
            [
                86.2,
                134.8
            ],
            [
                87.4,
                138.0
            ],
            [
                86.0,
                141.0
            ]
        ],
        "shift": null,
        "channel": 0,
        "closest_Dend": 0
    },
    {
        "type": 0,
        "location": [
            100,
            140
        ],
        "bgloc": [
            116,
            179
        ],
        "mean": [
            [
                31.976802
            ]
        ],
        "min": [
            [
                3
            ]
        ],
        "max": [
            [
                77
            ]
        ],
        "RawIntDen": [
            [
                1598
            ]
        ],
        "IntDen": [
            [
                15.988401000000001
            ]
        ],
        "local_bg": [
            [
                0.0
            ]
        ],
        "area": [
            0.5000000000000001
        ],
        "distance": 8.849134261003158,
        "points": [
            [
                100.0,
                143.8
            ],
            [
                97.4,
                142.6
            ],
            [
                96.8,
                140.0
            ],
            [
                97.0,
                137.0
            ],
            [
                100.0,
                135.6
            ],
            [
                103.4,
                136.6
            ],
            [
                104.8,
                140.0
            ],
            [
                103.2,
                143.2
            ]
        ],
        "shift": null,
        "channel": 0,
        "closest_Dend": 0
    },
    {
        "type": 0,
        "location": [
            94,
            107
        ],
        "bgloc": [
            84,
            86
        ],
        "mean": [
            [
                64.42905113636364
            ]
        ],
        "min": [
            [
                7
            ]
        ],
        "max": [
            [
                118
            ]
        ],
        "RawIntDen": [
            [
                5669
            ]
        ],
        "IntDen": [
            [
                56.69756500000002
            ]
        ],
        "local_bg": [
            [
                0.4090499999999999
            ]
        ],
        "area": [
            0.8800000000000001
        ],
        "distance": 9.628301100532147,
        "points": [
            [
                94.0,
                111.8
            ],
            [
                89.6,
                111.4
            ],
            [
                88.8,
                107.0
            ],
            [
                91.0,
                104.0
            ],
            [
                94.0,
                102.8
            ],
            [
                97.8,
                103.2
            ],
            [
                102.4,
                107.0
            ],
            [
                98.0,
                111.0
            ]
        ],
        "shift": null,
        "channel": 0,
        "closest_Dend": 0
    },
    {
        "type": 0,
        "location": [
            123,
            125
        ],
        "bgloc": [
            126,
            155
        ],
        "mean": [
            [
                14.707620000000002
            ]
        ],
        "min": [
            [
                1
            ]
        ],
        "max": [
            [
                39
            ]
        ],
        "RawIntDen": [
            [
                808
            ]
        ],
        "IntDen": [
            [
                8.089191000000003
            ]
        ],
        "local_bg": [
            [
                0.19998
            ]
        ],
        "area": [
            0.5500000000000002
        ],
        "distance": 12.05248735042988,
        "points": [
            [
                123.0,
                128.6
            ],
            [
                120.2,
                127.8
            ],
            [
                118.8,
                125.0
            ],
            [
                118.0,
                120.0
            ],
            [
                123.0,
                121.8
            ],
            [
                126.0,
                122.0
            ],
            [
                126.8,
                125.0
            ],
            [
                126.0,
                128.0
            ]
        ],
        "shift": null,
        "channel": 0,
        "closest_Dend": 0
    },
    {
        "type": 0,
        "location": [
            125,
            131
        ],
        "bgloc": [
            129,
            173
        ],
        "mean": [
            [
                24.95205
            ]
        ],
        "min": [
            [
                2
            ]
        ],
        "max": [
            [
                61
            ]
        ],
        "RawIntDen": [
            [
                1097
            ]
        ],
        "IntDen": [
            [
                10.978902000000003
            ]
        ],
        "local_bg": [
            [
                0.068175
            ]
        ],
        "area": [
            0.44000000000000006
        ],
        "distance": 12.19179255705928,
        "points": [
            [
                125.0,
                134.8
            ],
            [
                122.6,
                133.4
            ],
            [
                121.8,
                131.0
            ],
            [
                122.2,
                128.2
            ],
            [
                125.0,
                127.2
            ],
            [
                128.0,
                128.0
            ],
            [
                129.2,
                131.0
            ],
            [
                128.0,
                134.0
            ]
        ],
        "shift": null,
        "channel": 0,
        "closest_Dend": 0
    },
    {
        "type": 0,
        "location": [
            131,
            134
        ],
        "bgloc": [
            137,
            183
        ],
        "mean": [
            [
                31.996800000000004
            ]
        ],
        "min": [
            [
                4
            ]
        ],
        "max": [
            [
                73
            ]
        ],
        "RawIntDen": [
            [
                1439
            ]
        ],
        "IntDen": [
            [
                14.398560000000005
            ]
        ],
        "local_bg": [
            [
                0.022219999999999997
            ]
        ],
        "area": [
            0.45000000000000007
        ],
        "distance": 12.721615369427395,
        "points": [
            [
                131.0,
                137.4
            ],
            [
                128.2,
                136.8
            ],
            [
                127.2,
                134.0
            ],
            [
                128.0,
                131.0
            ],
            [
                131.0,
                130.0
            ],
            [
                134.0,
                131.0
            ],
            [
                134.2,
                134.0
            ],
            [
                133.8,
                136.8
            ]
        ],
        "shift": null,
        "channel": 0,
        "closest_Dend": 0
    },
    {
        "type": 0,
        "location": [
            136,
            135
        ],
        "bgloc": [
            142,
            188
        ],
        "mean": [
            [
                32.866278260869564
            ]
        ],
        "min": [
            [
                4
            ]
        ],
        "max": [
            [
                83
            ]
        ],
        "RawIntDen": [
            [
                1511
            ]
        ],
        "IntDen": [
            [
                15.118488000000003
            ]
        ],
        "local_bg": [
            [
                0.0
            ]
        ],
        "area": [
            0.4600000000000001
        ],
        "distance": 13.180543887407467,
        "points": [
            [
                136.0,
                139.0
            ],
            [
                133.0,
                138.0
            ],
            [
                132.8,
                135.0
            ],
            [
                133.2,
                132.2
            ],
            [
                136.0,
                131.0
            ],
            [
                139.0,
                132.0
            ],
            [
                139.8,
                135.0
            ],
            [
                138.6,
                137.6
            ]
        ],
        "shift": null,
        "channel": 0,
        "closest_Dend": 0
    },
    {
        "type": 0,
        "location": [
            139,
            126
        ],
        "bgloc": [
            143,
            162
        ],
        "mean": [
            [
                26.5428
            ]
        ],
        "min": [
            [
                3
            ]
        ],
        "max": [
            [
                67
            ]
        ],
        "RawIntDen": [
            [
                1459
            ]
        ],
        "IntDen": [
            [
                14.598540000000003
            ]
        ],
        "local_bg": [
            [
                0.018179999999999998
            ]
        ],
        "area": [
            0.5500000000000002
        ],
        "distance": 13.589858511551853,
        "points": [
            [
                139.0,
                130.6
            ],
            [
                136.0,
                129.0
            ],
            [
                135.2,
                126.0
            ],
            [
                136.2,
                123.2
            ],
            [
                139.0,
                122.0
            ],
            [
                142.2,
                122.8
            ],
            [
                143.8,
                126.0
            ],
            [
                142.4,
                129.4
            ]
        ],
        "shift": null,
        "channel": 0,
        "closest_Dend": 0
    },
    {
        "type": 0,
        "location": [
            150,
            100
        ],
        "bgloc": [
            147,
            83
        ],
        "mean": [
            [
                38.453490566037736
            ]
        ],
        "min": [
            [
                9
            ]
        ],
        "max": [
            [
                96
            ]
        ],
        "RawIntDen": [
            [
                2038
            ]
        ],
        "IntDen": [
            [
                20.380350000000004
            ]
        ],
        "local_bg": [
            [
                1.5658811320754715
            ]
        ],
        "area": [
            0.5300000000000001
        ],
        "distance": 15.39928543390683,
        "points": [
            [
                150.0,
                104.8
            ],
            [
                146.6,
                103.4
            ],
            [
                145.6,
                100.0
            ],
            [
                147.2,
                97.2
            ],
            [
                150.0,
                96.6
            ],
            [
                153.0,
                97.0
            ],
            [
                153.8,
                100.0
            ],
            [
                153.6,
                103.6
            ]
        ],
        "shift": null,
        "channel": 0,
        "closest_Dend": 0
    },
    {
        "type": 0,
        "location": [
            148,
            95
        ],
        "bgloc": [
            144,
            68
        ],
        "mean": [
            [
                27.9972
            ]
        ],
        "min": [
            [
                1
            ]
        ],
        "max": [
            [
                74
            ]
        ],
        "RawIntDen": [
            [
                1287
            ]
        ],
        "IntDen": [
            [
                12.878712000000004
            ]
        ],
        "local_bg": [
            [
                16.976563043478258
            ]
        ],
        "area": [
            0.4600000000000001
        ],
        "distance": 15.526564654520412,
        "points": [
            [
                148.0,
                98.4
            ],
            [
                145.0,
                98.0
            ],
            [
                144.2,
                95.0
            ],
            [
                145.2,
                92.2
            ],
            [
                148.0,
                91.8
            ],
            [
                151.0,
                92.0
            ],
            [
                152.2,
                95.0
            ],
            [
                150.8,
                97.8
            ]
        ],
        "shift": null,
        "channel": 0,
        "closest_Dend": 0
    },
    {
        "type": 0,
        "location": [
            156,
            98
        ],
        "bgloc": [
            153,
            79
        ],
        "mean": [
            [
                28.957888235294117
            ]
        ],
        "min": [
            [
                3
            ]
        ],
        "max": [
            [
                76
            ]
        ],
        "RawIntDen": [
            [
                1476
            ]
        ],
        "IntDen": [
            [
                14.768523000000004
            ]
        ],
        "local_bg": [
            [
                3.3722117647058822
            ]
        ],
        "area": [
            0.5100000000000001
        ],
        "distance": 15.653843875133987,
        "points": [
            [
                156.0,
                103.0
            ],
            [
                153.0,
                101.0
            ],
            [
                152.2,
                98.0
            ],
            [
                153.0,
                95.0
            ],
            [
                156.0,
                94.8
            ],
            [
                159.0,
                95.0
            ],
            [
                159.4,
                98.0
            ],
            [
                158.8,
                100.8
            ]
        ],
        "shift": null,
        "channel": 0,
        "closest_Dend": 0
    },
    {
        "type": 0,
        "location": [
            161,
            100
        ],
        "bgloc": [
            159,
            86
        ],
        "mean": [
            [
                48.225514893617024
            ]
        ],
        "min": [
            [
                9
            ]
        ],
        "max": [
            [
                97
            ]
        ],
        "RawIntDen": [
            [
                2266
            ]
        ],
        "IntDen": [
            [
                22.665992000000006
            ]
        ],
        "local_bg": [
            [
                1.9998
            ]
        ],
        "area": [
            0.4700000000000001
        ],
        "distance": 16.12053435071711,
        "points": [
            [
                161.0,
                103.8
            ],
            [
                156.8,
                104.2
            ],
            [
                157.6,
                100.0
            ],
            [
                158.2,
                97.2
            ],
            [
                161.0,
                96.6
            ],
            [
                163.8,
                97.2
            ],
            [
                165.0,
                100.0
            ],
            [
                164.2,
                103.2
            ]
        ],
        "shift": null,
        "channel": 0,
        "closest_Dend": 0
    },
    {
        "type": 0,
        "location": [
            166,
            97
        ],
        "bgloc": [
            166,
            77
        ],
        "mean": [
            [
                37.537123880597015
            ]
        ],
        "min": [
            [
                12
            ]
        ],
        "max": [
            [
                88
            ]
        ],
        "RawIntDen": [
            [
                2514
            ]
        ],
        "IntDen": [
            [
                25.149873000000003
            ]
        ],
        "local_bg": [
            [
                47.55364626865672
            ]
        ],
        "area": [
            0.6700000000000002
        ],
        "distance": 16.522544451984878,
        "points": [
            [
                166.0,
                101.2
            ],
            [
                163.2,
                99.8
            ],
            [
                162.4,
                97.0
            ],
            [
                163.0,
                94.0
            ],
            [
                166.0,
                93.0
            ],
            [
                169.0,
                94.0
            ],
            [
                172.2,
                97.0
            ],
            [
                170.8,
                101.8
            ]
        ],
        "shift": null,
        "channel": 0,
        "closest_Dend": 0
    },
    {
        "type": 0,
        "location": [
            175,
            116
        ],
        "bgloc": [
            175,
            134
        ],
        "mean": [
            [
                48.647965625
            ]
        ],
        "min": [
            [
                4
            ]
        ],
        "max": [
            [
                159
            ]
        ],
        "RawIntDen": [
            [
                3113
            ]
        ],
        "IntDen": [
            [
                31.134698000000004
            ]
        ],
        "local_bg": [
            [
                0.7499249999999998
            ]
        ],
        "area": [
            0.6400000000000001
        ],
        "distance": 17.82254445198488,
        "points": [
            [
                175.0,
                119.6
            ],
            [
                172.2,
                118.8
            ],
            [
                171.4,
                116.0
            ],
            [
                170.8,
                111.8
            ],
            [
                175.0,
                110.8
            ],
            [
                179.2,
                111.8
            ],
            [
                179.6,
                116.0
            ],
            [
                178.0,
                119.0
            ]
        ],
        "shift": null,
        "channel": 0,
        "closest_Dend": 0
    },
    {
        "type": 0,
        "location": [
            186,
            118
        ],
        "bgloc": [
            186,
            140
        ],
        "mean": [
            [
                53.441024000000006
            ]
        ],
        "min": [
            [
                5
            ]
        ],
        "max": [
            [
                119
            ]
        ],
        "RawIntDen": [
            [
                4008
            ]
        ],
        "IntDen": [
            [
                40.08076800000001
            ]
        ],
        "local_bg": [
            [
                0.5866079999999999
            ]
        ],
        "area": [
            0.7500000000000001
        ],
        "distance": 18.522544451984878,
        "points": [
            [
                186.0,
                122.6
            ],
            [
                183.0,
                121.0
            ],
            [
                181.4,
                118.0
            ],
            [
                182.0,
                114.0
            ],
            [
                186.0,
                112.2
            ],
            [
                190.0,
                114.0
            ],
            [
                191.0,
                118.0
            ],
            [
                189.2,
                121.2
            ]
        ],
        "shift": null,
        "channel": 0,
        "closest_Dend": 0
    },
    {
        "type": 0,
        "location": [
            189,
            125
        ],
        "bgloc": [
            189,
            161
        ],
        "mean": [
            [
                18.651980769230768
            ]
        ],
        "min": [
            [
                1
            ]
        ],
        "max": [
            [
                54
            ]
        ],
        "RawIntDen": [
            [
                969
            ]
        ],
        "IntDen": [
            [
                9.69903
            ]
        ],
        "local_bg": [
            [
                0.038457692307692304
            ]
        ],
        "area": [
            0.5200000000000001
        ],
        "distance": 18.82254445198488,
        "points": [
            [
                189.0,
                128.6
            ],
            [
                186.2,
                127.8
            ],
            [
                185.0,
                125.0
            ],
            [
                185.8,
                121.8
            ],
            [
                189.0,
                120.4
            ],
            [
                192.2,
                121.8
            ],
            [
                192.6,
                125.0
            ],
            [
                192.0,
                128.0
            ]
        ],
        "shift": null,
        "channel": 0,
        "closest_Dend": 0
    },
    {
        "type": 0,
        "location": [
            205,
            118
        ],
        "bgloc": [
            205,
            138
        ],
        "mean": [
            [
                55.718931250000004
            ]
        ],
        "min": [
            [
                5
            ]
        ],
        "max": [
            [
                164
            ]
        ],
        "RawIntDen": [
            [
                3566
            ]
        ],
        "IntDen": [
            [
                35.66011600000001
            ]
        ],
        "local_bg": [
            [
                0.6405609375
            ]
        ],
        "area": [
            0.6400000000000001
        ],
        "distance": 20.425320089716873,
        "points": [
            [
                205.0,
                122.0
            ],
            [
                202.0,
                121.0
            ],
            [
                201.8,
                118.0
            ],
            [
                202.2,
                115.2
            ],
            [
                205.0,
                112.2
            ],
            [
                210.2,
                112.8
            ],
            [
                209.2,
                118.0
            ],
            [
                208.0,
                121.0
            ]
        ],
        "shift": null,
        "channel": 0,
        "closest_Dend": 0
    },
    {
        "type": 0,
        "location": [
            198,
            96
        ],
        "bgloc": [
            198,
            72
        ],
        "mean": [
            [
                37.715329213483145
            ]
        ],
        "min": [
            [
                7
            ]
        ],
        "max": [
            [
                77
            ]
        ],
        "RawIntDen": [
            [
                3356
            ]
        ],
        "IntDen": [
            [
                33.566643000000006
            ]
        ],
        "local_bg": [
            [
                0.4381584269662921
            ]
        ],
        "area": [
            0.8900000000000001
        ],
        "distance": 20.725320089716874,
        "points": [
            [
                198.0,
                102.0
            ],
            [
                194.2,
                99.8
            ],
            [
                188.8,
                96.0
            ],
            [
                194.8,
                92.8
            ],
            [
                198.0,
                92.6
            ],
            [
                201.0,
                93.0
            ],
            [
                203.6,
                96.0
            ],
            [
                202.0,
                100.0
            ]
        ],
        "shift": null,
        "channel": 0,
        "closest_Dend": 0
    },
    {
        "type": 0,
        "location": [
            239,
            93
        ],
        "bgloc": [
            235,
            68
        ],
        "mean": [
            [
                23.523963157894737
            ]
        ],
        "min": [
            [
                2
            ]
        ],
        "max": [
            [
                62
            ]
        ],
        "RawIntDen": [
            [
                1340
            ]
        ],
        "IntDen": [
            [
                13.408659000000002
            ]
        ],
        "local_bg": [
            [
                0.21050526315789472
            ]
        ],
        "area": [
            0.5700000000000001
        ],
        "distance": 23.994314863567332,
        "points": [
            [
                239.0,
                97.0
            ],
            [
                236.0,
                96.0
            ],
            [
                234.0,
                93.0
            ],
            [
                236.2,
                90.2
            ],
            [
                239.0,
                89.8
            ],
            [
                242.0,
                90.0
            ],
            [
                244.4,
                93.0
            ],
            [
                242.6,
                96.6
            ]
        ],
        "shift": null,
        "channel": 0,
        "closest_Dend": 0
    },
    {
        "type": 0,
        "location": [
            244,
            118
        ],
        "bgloc": [
            245,
            142
        ],
        "mean": [
            [
                24.126619354838706
            ]
        ],
        "min": [
            [
                1
            ]
        ],
        "max": [
            [
                76
            ]
        ],
        "RawIntDen": [
            [
                1495
            ]
        ],
        "IntDen": [
            [
                14.958504000000001
            ]
        ],
        "local_bg": [
            [
                0.49995
            ]
        ],
        "area": [
            0.6200000000000001
        ],
        "distance": 24.26353941778549,
        "points": [
            [
                244.0,
                121.8
            ],
            [
                241.0,
                121.0
            ],
            [
                239.6,
                118.0
            ],
            [
                240.6,
                114.6
            ],
            [
                244.0,
                112.6
            ],
            [
                248.6,
                113.4
            ],
            [
                248.0,
                118.0
            ],
            [
                246.6,
                120.6
            ]
        ],
        "shift": null,
        "channel": 0,
        "closest_Dend": 0
    },
    {
        "type": 0,
        "location": [
            255,
            93
        ],
        "bgloc": [
            253,
            69
        ],
        "mean": [
            [
                29.438232352941174
            ]
        ],
        "min": [
            [
                5
            ]
        ],
        "max": [
            [
                65
            ]
        ],
        "RawIntDen": [
            [
                2001
            ]
        ],
        "IntDen": [
            [
                20.017998000000002
            ]
        ],
        "local_bg": [
            [
                0.30879264705882353
            ]
        ],
        "area": [
            0.6800000000000002
        ],
        "distance": 25.508446283156662,
        "points": [
            [
                255.0,
                98.6
            ],
            [
                252.0,
                96.0
            ],
            [
                251.2,
                93.0
            ],
            [
                252.4,
                90.4
            ],
            [
                255.0,
                89.2
            ],
            [
                258.2,
                89.8
            ],
            [
                260.2,
                93.0
            ],
            [
                260.8,
                98.8
            ]
        ],
        "shift": null,
        "channel": 0,
        "closest_Dend": 0
    },
    {
        "type": 0,
        "location": [
            293,
            115
        ],
        "bgloc": [
            293,
            137
        ],
        "mean": [
            [
                24.2016612244898
            ]
        ],
        "min": [
            [
                5
            ]
        ],
        "max": [
            [
                66
            ]
        ],
        "RawIntDen": [
            [
                1185
            ]
        ],
        "IntDen": [
            [
                11.858814000000004
            ]
        ],
        "local_bg": [
            [
                40.85793061224489
            ]
        ],
        "area": [
            0.4900000000000001
        ],
        "distance": 29.24032418281925,
        "points": [
            [
                293.0,
                118.6
            ],
            [
                290.2,
                117.8
            ],
            [
                288.8,
                115.0
            ],
            [
                290.0,
                112.0
            ],
            [
                293.0,
                110.8
            ],
            [
                296.4,
                111.6
            ],
            [
                296.8,
                115.0
            ],
            [
                295.8,
                117.8
            ]
        ],
        "shift": null,
        "channel": 0,
        "closest_Dend": 0
    },
    {
        "type": 0,
        "location": [
            301,
            85
        ],
        "bgloc": [
            301,
            47
        ],
        "mean": [
            [
                10.487839999999998
            ]
        ],
        "min": [
            [
                1
            ]
        ],
        "max": [
            [
                36
            ]
        ],
        "RawIntDen": [
            [
                471
            ]
        ],
        "IntDen": [
            [
                4.719528
            ]
        ],
        "local_bg": [
            [
                0.022219999999999997
            ]
        ],
        "area": [
            0.45000000000000007
        ],
        "distance": 30.04032418281925,
        "points": [
            [
                301.0,
                89.0
            ],
            [
                298.2,
                87.8
            ],
            [
                297.6,
                85.0
            ],
            [
                298.2,
                82.2
            ],
            [
                301.0,
                81.8
            ],
            [
                304.0,
                82.0
            ],
            [
                304.6,
                85.0
            ],
            [
                304.0,
                88.0
            ]
        ],
        "shift": null,
        "channel": 0,
        "closest_Dend": 0
    },
    {
        "type": 0,
        "location": [
            321,
            86
        ],
        "bgloc": [
            321,
            50
        ],
        "mean": [
            [
                17.01716603773585
            ]
        ],
        "min": [
            [
                1
            ]
        ],
        "max": [
            [
                47
            ]
        ],
        "RawIntDen": [
            [
                901
            ]
        ],
        "IntDen": [
            [
                9.019098000000003
            ]
        ],
        "local_bg": [
            [
                0.03773207547169811
            ]
        ],
        "area": [
            0.5300000000000001
        ],
        "distance": 32.040324182819255,
        "points": [
            [
                321.0,
                89.8
            ],
            [
                318.0,
                89.0
            ],
            [
                315.6,
                86.0
            ],
            [
                318.0,
                83.0
            ],
            [
                321.0,
                82.8
            ],
            [
                324.0,
                83.0
            ],
            [
                325.2,
                86.0
            ],
            [
                323.8,
                88.8
            ]
        ],
        "shift": null,
        "channel": 0,
        "closest_Dend": 0
    },
    {
        "type": 0,
        "location": [
            322,
            128
        ],
        "bgloc": [
            322,
            176
        ],
        "mean": [
            [
                58.454949295774654
            ]
        ],
        "min": [
            [
                15
            ]
        ],
        "max": [
            [
                105
            ]
        ],
        "RawIntDen": [
            [
                4150
            ]
        ],
        "IntDen": [
            [
                41.50301400000001
            ]
        ],
        "local_bg": [
            [
                0.04224929577464789
            ]
        ],
        "area": [
            0.7100000000000002
        ],
        "distance": 32.14032418281925,
        "points": [
            [
                322.0,
                132.8
            ],
            [
                319.0,
                131.0
            ],
            [
                316.8,
                128.0
            ],
            [
                318.2,
                124.2
            ],
            [
                322.0,
                122.6
            ],
            [
                325.2,
                124.8
            ],
            [
                327.0,
                128.0
            ],
            [
                325.6,
                131.6
            ]
        ],
        "shift": null,
        "channel": 0,
        "closest_Dend": 0
    },
    {
        "type": 0,
        "location": [
            324,
            91
        ],
        "bgloc": [
            324,
            65
        ],
        "mean": [
            [
                35.02744406779661
            ]
        ],
        "min": [
            [
                8
            ]
        ],
        "max": [
            [
                89
            ]
        ],
        "RawIntDen": [
            [
                2066
            ]
        ],
        "IntDen": [
            [
                20.666192000000006
            ]
        ],
        "local_bg": [
            [
                0.2881067796610169
            ]
        ],
        "area": [
            0.5900000000000001
        ],
        "distance": 32.34032418281925,
        "points": [
            [
                324.0,
                97.4
            ],
            [
                320.4,
                94.6
            ],
            [
                320.2,
                91.0
            ],
            [
                321.4,
                88.4
            ],
            [
                324.0,
                87.4
            ],
            [
                327.0,
                88.0
            ],
            [
                328.6,
                91.0
            ],
            [
                327.0,
                94.0
            ]
        ],
        "shift": null,
        "channel": 0,
        "closest_Dend": 0
    },
    {
        "type": 0,
        "location": [
            332,
            89
        ],
        "bgloc": [
            332,
            59
        ],
        "mean": [
            [
                63.28060181818182
            ]
        ],
        "min": [
            [
                8
            ]
        ],
        "max": [
            [
                132
            ]
        ],
        "RawIntDen": [
            [
                3480
            ]
        ],
        "IntDen": [
            [
                34.80433100000001
            ]
        ],
        "local_bg": [
            [
                0.07271999999999999
            ]
        ],
        "area": [
            0.5500000000000002
        ],
        "distance": 33.14032418281925,
        "points": [
            [
                332.0,
                93.8
            ],
            [
                328.8,
                92.2
            ],
            [
                327.2,
                89.0
            ],
            [
                328.8,
                85.8
            ],
            [
                332.0,
                85.2
            ],
            [
                334.8,
                86.2
            ],
            [
                336.2,
                89.0
            ],
            [
                335.2,
                92.2
            ]
        ],
        "shift": null,
        "channel": 0,
        "closest_Dend": 0
    },
    {
        "type": 0,
        "location": [
            348,
            93
        ],
        "bgloc": [
            348,
            71
        ],
        "mean": [
            [
                39.47397076923077
            ]
        ],
        "min": [
            [
                3
            ]
        ],
        "max": [
            [
                121
            ]
        ],
        "RawIntDen": [
            [
                2565
            ]
        ],
        "IntDen": [
            [
                25.658081000000003
            ]
        ],
        "local_bg": [
            [
                0.6307061538461538
            ]
        ],
        "area": [
            0.6500000000000001
        ],
        "distance": 34.74032418281926,
        "points": [
            [
                348.0,
                98.4
            ],
            [
                342.2,
                98.8
            ],
            [
                344.2,
                93.0
            ],
            [
                345.2,
                90.2
            ],
            [
                348.0,
                89.8
            ],
            [
                350.8,
                90.2
            ],
            [
                351.2,
                93.0
            ],
            [
                352.4,
                97.4
            ]
        ],
        "shift": null,
        "channel": 0,
        "closest_Dend": 0
    },
    {
        "type": 0,
        "location": [
            357,
            120
        ],
        "bgloc": [
            357,
            152
        ],
        "mean": [
            [
                38.869967105263164
            ]
        ],
        "min": [
            [
                9
            ]
        ],
        "max": [
            [
                89
            ]
        ],
        "RawIntDen": [
            [
                2954
            ]
        ],
        "IntDen": [
            [
                29.54117500000001
            ]
        ],
        "local_bg": [
            [
                0.2631315789473684
            ]
        ],
        "area": [
            0.7600000000000001
        ],
        "distance": 35.640324182819256,
        "points": [
            [
                357.0,
                125.8
            ],
            [
                353.8,
                123.2
            ],
            [
                352.6,
                120.0
            ],
            [
                354.0,
                117.0
            ],
            [
                357.0,
                116.0
            ],
            [
                360.4,
                116.6
            ],
            [
                363.8,
                120.0
            ],
            [
                361.6,
                124.6
            ]
        ],
        "shift": null,
        "channel": 0,
        "closest_Dend": 0
    },
    {
        "type": 0,
        "location": [
            369,
            123
        ],
        "bgloc": [
            369,
            161
        ],
        "mean": [
            [
                46.75479615384615
            ]
        ],
        "min": [
            [
                7
            ]
        ],
        "max": [
            [
                91
            ]
        ],
        "RawIntDen": [
            [
                3646
            ]
        ],
        "IntDen": [
            [
                36.468741
            ]
        ],
        "local_bg": [
            [
                0.07691538461538461
            ]
        ],
        "area": [
            0.7800000000000001
        ],
        "distance": 36.84032418281926,
        "points": [
            [
                369.0,
                130.0
            ],
            [
                365.6,
                126.4
            ],
            [
                362.2,
                123.0
            ],
            [
                364.8,
                118.8
            ],
            [
                369.0,
                118.8
            ],
            [
                372.8,
                119.2
            ],
            [
                373.0,
                123.0
            ],
            [
                372.2,
                126.2
            ]
        ],
        "shift": null,
        "channel": 0,
        "closest_Dend": 0
    },
    {
        "type": 0,
        "location": [
            376,
            84
        ],
        "bgloc": [
            376,
            44
        ],
        "mean": [
            [
                21.243158490566035
            ]
        ],
        "min": [
            [
                3
            ]
        ],
        "max": [
            [
                62
            ]
        ],
        "RawIntDen": [
            [
                1125
            ]
        ],
        "IntDen": [
            [
                11.258874
            ]
        ],
        "local_bg": [
            [
                0.018866037735849054
            ]
        ],
        "area": [
            0.5300000000000001
        ],
        "distance": 37.94032418281926,
        "points": [
            [
                376.0,
                88.6
            ],
            [
                373.2,
                86.8
            ],
            [
                372.2,
                84.0
            ],
            [
                373.0,
                81.0
            ],
            [
                376.0,
                79.4
            ],
            [
                379.0,
                81.0
            ],
            [
                379.6,
                84.0
            ],
            [
                379.0,
                87.0
            ]
        ],
        "shift": null,
        "channel": 0,
        "closest_Dend": 0
    },
    {
        "type": 0,
        "location": [
            389,
            80
        ],
        "bgloc": [
            383,
            33
        ],
        "mean": [
            [
                21.93658163265306
            ]
        ],
        "min": [
            [
                2
            ]
        ],
        "max": [
            [
                48
            ]
        ],
        "RawIntDen": [
            [
                1074
            ]
        ],
        "IntDen": [
            [
                10.748925000000002
            ]
        ],
        "local_bg": [
            [
                0.0
            ]
        ],
        "area": [
            0.4900000000000001
        ],
        "distance": 39.11868835827788,
        "points": [
            [
                389.0,
                84.6
            ],
            [
                385.2,
                83.8
            ],
            [
                385.0,
                80.0
            ],
            [
                386.2,
                77.2
            ],
            [
                389.0,
                76.8
            ],
            [
                391.6,
                77.4
            ],
            [
                393.0,
                80.0
            ],
            [
                392.0,
                83.0
            ]
        ],
        "shift": null,
        "channel": 0,
        "closest_Dend": 0
    },
    {
        "type": 0,
        "location": [
            397,
            121
        ],
        "bgloc": [
            401,
            157
        ],
        "mean": [
            [
                24.606914062499996
            ]
        ],
        "min": [
            [
                4
            ]
        ],
        "max": [
            [
                70
            ]
        ],
        "RawIntDen": [
            [
                1574
            ]
        ],
        "IntDen": [
            [
                15.748425000000001
            ]
        ],
        "local_bg": [
            [
                0.062493749999999994
            ]
        ],
        "area": [
            0.6400000000000001
        ],
        "distance": 39.43415972670985,
        "points": [
            [
                397.0,
                125.6
            ],
            [
                394.0,
                124.0
            ],
            [
                394.0,
                121.0
            ],
            [
                394.0,
                118.0
            ],
            [
                397.0,
                116.0
            ],
            [
                401.8,
                116.2
            ],
            [
                401.6,
                121.0
            ],
            [
                400.4,
                124.4
            ]
        ],
        "shift": null,
        "channel": 0,
        "closest_Dend": 0
    },
    {
        "type": 0,
        "location": [
            395,
            84
        ],
        "bgloc": [
            390,
            46
        ],
        "mean": [
            [
                48.04426818181818
            ]
        ],
        "min": [
            [
                13
            ]
        ],
        "max": [
            [
                91
            ]
        ],
        "RawIntDen": [
            [
                3170
            ]
        ],
        "IntDen": [
            [
                31.709217000000006
            ]
        ],
        "local_bg": [
            [
                0.0
            ]
        ],
        "area": [
            0.6600000000000001
        ],
        "distance": 39.667842221844644,
        "points": [
            [
                395.0,
                89.8
            ],
            [
                391.6,
                87.4
            ],
            [
                390.4,
                84.0
            ],
            [
                392.0,
                81.0
            ],
            [
                395.0,
                79.0
            ],
            [
                398.2,
                80.8
            ],
            [
                399.6,
                84.0
            ],
            [
                398.2,
                87.2
            ]
        ],
        "shift": null,
        "channel": 0,
        "closest_Dend": 0
    },
    {
        "type": 0,
        "location": [
            400,
            91
        ],
        "bgloc": [
            397,
            68
        ],
        "mean": [
            [
                42.54018805970149
            ]
        ],
        "min": [
            [
                7
            ]
        ],
        "max": [
            [
                128
            ]
        ],
        "RawIntDen": [
            [
                2850
            ]
        ],
        "IntDen": [
            [
                28.501926000000005
            ]
        ],
        "local_bg": [
            [
                0.6864985074626865
            ]
        ],
        "area": [
            0.6700000000000002
        ],
        "distance": 40.413293614647614,
        "points": [
            [
                400.0,
                96.4
            ],
            [
                395.0,
                96.0
            ],
            [
                395.2,
                91.0
            ],
            [
                397.0,
                88.0
            ],
            [
                400.0,
                86.8
            ],
            [
                403.0,
                88.0
            ],
            [
                403.8,
                91.0
            ],
            [
                403.0,
                94.0
            ]
        ],
        "shift": null,
        "channel": 0,
        "closest_Dend": 0
    },
    {
        "type": 0,
        "location": [
            403,
            126
        ],
        "bgloc": [
            408,
            173
        ],
        "mean": [
            [
                27.428629411764703
            ]
        ],
        "min": [
            [
                6
            ]
        ],
        "max": [
            [
                62
            ]
        ],
        "RawIntDen": [
            [
                1398
            ]
        ],
        "IntDen": [
            [
                13.988601000000001
            ]
        ],
        "local_bg": [
            [
                0.0
            ]
        ],
        "area": [
            0.5100000000000001
        ],
        "distance": 40.549731822695726,
        "points": [
            [
                403.0,
                129.4
            ],
            [
                399.6,
                129.4
            ],
            [
                398.2,
                126.0
            ],
            [
                399.6,
                122.6
            ],
            [
                403.0,
                122.6
            ],
            [
                405.8,
                123.2
            ],
            [
                407.4,
                126.0
            ],
            [
                406.0,
                129.0
            ]
        ],
        "shift": null,
        "channel": 0,
        "closest_Dend": 0
    },
    {
        "type": 0,
        "location": [
            406,
            93
        ],
        "bgloc": [
            403,
            76
        ],
        "mean": [
            [
                50.41535714285715
            ]
        ],
        "min": [
            [
                11
            ]
        ],
        "max": [
            [
                191
            ]
        ],
        "RawIntDen": [
            [
                2823
            ]
        ],
        "IntDen": [
            [
                28.23260000000001
            ]
        ],
        "local_bg": [
            [
                1.6426928571428572
            ]
        ],
        "area": [
            0.56
        ],
        "distance": 40.661363083826025,
        "points": [
            [
                406.0,
                97.8
            ],
            [
                402.4,
                96.6
            ],
            [
                402.4,
                93.0
            ],
            [
                403.0,
                90.0
            ],
            [
                406.0,
                89.2
            ],
            [
                409.0,
                90.0
            ],
            [
                410.8,
                93.0
            ],
            [
                409.4,
                96.4
            ]
        ],
        "shift": null,
        "channel": 0,
        "closest_Dend": 0
    },
    {
        "type": 0,
        "location": [
            411,
            87
        ],
        "bgloc": [
            407,
            59
        ],
        "mean": [
            [
                52.4630375
            ]
        ],
        "min": [
            [
                10
            ]
        ],
        "max": [
            [
                106
            ]
        ],
        "RawIntDen": [
            [
                3777
            ]
        ],
        "IntDen": [
            [
                37.77338700000001
            ]
        ],
        "local_bg": [
            [
                0.3471875
            ]
        ],
        "area": [
            0.7200000000000002
        ],
        "distance": 41.23192286293638,
        "points": [
            [
                411.0,
                91.8
            ],
            [
                408.0,
                90.0
            ],
            [
                407.0,
                87.0
            ],
            [
                408.0,
                84.0
            ],
            [
                411.0,
                83.0
            ],
            [
                414.2,
                83.8
            ],
            [
                416.8,
                87.0
            ],
            [
                416.4,
                92.4
            ]
        ],
        "shift": null,
        "channel": 0,
        "closest_Dend": 0
    },
    {
        "type": 0,
        "location": [
            423,
            116
        ],
        "bgloc": [
            424,
            147
        ],
        "mean": [
            [
                25.071566666666666
            ]
        ],
        "min": [
            [
                3
            ]
        ],
        "max": [
            [
                62
            ]
        ],
        "RawIntDen": [
            [
                1353
            ]
        ],
        "IntDen": [
            [
                13.538646000000002
            ]
        ],
        "local_bg": [
            [
                0.33329999999999993
            ]
        ],
        "area": [
            0.5400000000000001
        ],
        "distance": 42.16812044939428,
        "points": [
            [
                423.0,
                119.8
            ],
            [
                420.0,
                119.0
            ],
            [
                418.6,
                116.0
            ],
            [
                420.0,
                113.0
            ],
            [
                423.0,
                111.4
            ],
            [
                426.0,
                113.0
            ],
            [
                427.0,
                116.0
            ],
            [
                426.0,
                119.0
            ]
        ],
        "shift": null,
        "channel": 0,
        "closest_Dend": 0
    },
    {
        "type": 0,
        "location": [
            426,
            88
        ],
        "bgloc": [
            426,
            64
        ],
        "mean": [
            [
                109.25212319999999
            ]
        ],
        "min": [
            [
                37
            ]
        ],
        "max": [
            [
                201
            ]
        ],
        "RawIntDen": [
            [
                13656
            ]
        ],
        "IntDen": [
            [
                136.565154
            ]
        ],
        "local_bg": [
            [
                0.5519448
            ]
        ],
        "area": [
            1.2500000000000002
        ],
        "distance": 42.96121287110413,
        "points": [
            [
                426.0,
                94.4
            ],
            [
                421.4,
                92.6
            ],
            [
                417.8,
                88.0
            ],
            [
                421.6,
                83.6
            ],
            [
                426.0,
                82.6
            ],
            [
                430.0,
                84.0
            ],
            [
                433.0,
                88.0
            ],
            [
                431.2,
                93.2
            ]
        ],
        "shift": null,
        "channel": 0,
        "closest_Dend": 0
    },
    {
        "type": 0,
        "location": [
            433,
            114
        ],
        "bgloc": [
            433,
            142
        ],
        "mean": [
            [
                34.9136294117647
            ]
        ],
        "min": [
            [
                4
            ]
        ],
        "max": [
            [
                144
            ]
        ],
        "RawIntDen": [
            [
                2967
            ]
        ],
        "IntDen": [
            [
                29.676585000000006
            ]
        ],
        "local_bg": [
            [
                0.7058117647058822
            ]
        ],
        "area": [
            0.8500000000000002
        ],
        "distance": 43.261212871104135,
        "points": [
            [
                433.0,
                118.4
            ],
            [
                430.0,
                117.0
            ],
            [
                427.8,
                114.0
            ],
            [
                427.4,
                108.4
            ],
            [
                433.0,
                108.2
            ],
            [
                438.0,
                109.0
            ],
            [
                437.6,
                114.0
            ],
            [
                436.0,
                117.0
            ]
        ],
        "shift": null,
        "channel": 0,
        "closest_Dend": 0
    },
    {
        "type": 0,
        "location": [
            433,
            114
        ],
        "bgloc": [
            433,
            142
        ],
        "mean": [
            [
                34.9136294117647
            ]
        ],
        "min": [
            [
                4
            ]
        ],
        "max": [
            [
                144
            ]
        ],
        "RawIntDen": [
            [
                2967
            ]
        ],
        "IntDen": [
            [
                29.676585000000006
            ]
        ],
        "local_bg": [
            [
                0.7058117647058822
            ]
        ],
        "area": [
            0.8500000000000002
        ],
        "distance": 43.261212871104135,
        "points": [
            [
                433.0,
                118.4
            ],
            [
                430.0,
                117.0
            ],
            [
                427.8,
                114.0
            ],
            [
                427.4,
                108.4
            ],
            [
                433.0,
                108.2
            ],
            [
                438.0,
                109.0
            ],
            [
                437.6,
                114.0
            ],
            [
                436.0,
                117.0
            ]
        ],
        "shift": null,
        "channel": 0,
        "closest_Dend": 0
    },
    {
        "type": 0,
        "location": [
            458,
            121
        ],
        "bgloc": [
            449,
            158
        ],
        "mean": [
            [
                30.0810612244898
            ]
        ],
        "min": [
            [
                2
            ]
        ],
        "max": [
            [
                115
            ]
        ],
        "RawIntDen": [
            [
                2947
            ]
        ],
        "IntDen": [
            [
                29.47944000000001
            ]
        ],
        "local_bg": [
            [
                0.18365510204081634
            ]
        ],
        "area": [
            0.9800000000000002
        ],
        "distance": 46.20247906863369,
        "points": [
            [
                458.0,
                126.2
            ],
            [
                454.8,
                124.2
            ],
            [
                454.6,
                121.0
            ],
            [
                454.8,
                117.8
            ],
            [
                458.0,
                112.8
            ],
            [
                465.2,
                113.8
            ],
            [
                463.0,
                121.0
            ],
            [
                461.2,
                124.2
            ]
        ],
        "shift": null,
        "channel": 0,
        "closest_Dend": 0
    },
    {
        "type": 0,
        "location": [
            470,
            124
        ],
        "bgloc": [
            465,
            163
        ],
        "mean": [
            [
                30.099947222222227
            ]
        ],
        "min": [
            [
                3
            ]
        ],
        "max": [
            [
                105
            ]
        ],
        "RawIntDen": [
            [
                2167
            ]
        ],
        "IntDen": [
            [
                21.671962000000008
            ]
        ],
        "local_bg": [
            [
                0.18053749999999996
            ]
        ],
        "area": [
            0.7200000000000002
        ],
        "distance": 48.16997789442347,
        "points": [
            [
                470.0,
                129.2
            ],
            [
                466.4,
                127.6
            ],
            [
                466.0,
                124.0
            ],
            [
                466.8,
                120.8
            ],
            [
                470.0,
                114.8
            ],
            [
                473.2,
                120.8
            ],
            [
                473.8,
                124.0
            ],
            [
                472.8,
                126.8
            ]
        ],
        "shift": null,
        "channel": 0,
        "closest_Dend": 0
    },
    {
        "type": 0,
        "location": [
            486,
            128
        ],
        "bgloc": [
            477,
            169
        ],
        "mean": [
            [
                19.368433333333332
            ]
        ],
        "min": [
            [
                2
            ]
        ],
        "max": [
            [
                56
            ]
        ],
        "RawIntDen": [
            [
                1045
            ]
        ],
        "IntDen": [
            [
                10.458954
            ]
        ],
        "local_bg": [
            [
                0.07406666666666666
            ]
        ],
        "area": [
            0.5400000000000001
        ],
        "distance": 49.04678871614634,
        "points": [
            [
                486.0,
                132.4
            ],
            [
                483.0,
                131.0
            ],
            [
                482.8,
                128.0
            ],
            [
                483.2,
                125.2
            ],
            [
                486.0,
                122.4
            ],
            [
                489.4,
                124.6
            ],
            [
                490.2,
                128.0
            ],
            [
                489.0,
                131.0
            ]
        ],
        "shift": null,
        "channel": 0,
        "closest_Dend": 0
    },
    {
        "type": 0,
        "location": [
            494,
            90
        ],
        "bgloc": [
            498,
            56
        ],
        "mean": [
            [
                86.11912972972974
            ]
        ],
        "min": [
            [
                20
            ]
        ],
        "max": [
            [
                180
            ]
        ],
        "RawIntDen": [
            [
                6372
            ]
        ],
        "IntDen": [
            [
                63.72815600000001
            ]
        ],
        "local_bg": [
            [
                0.2702432432432433
            ]
        ],
        "area": [
            0.7400000000000001
        ],
        "distance": 49.1819555255886,
        "points": [
            [
                494.0,
                94.6
            ],
            [
                491.0,
                93.0
            ],
            [
                489.0,
                90.0
            ],
            [
                490.8,
                86.8
            ],
            [
                494.0,
                86.0
            ],
            [
                497.2,
                86.8
            ],
            [
                501.0,
                90.0
            ],
            [
                498.6,
                94.6
            ]
        ],
        "shift": null,
        "channel": 0,
        "closest_Dend": 0
    },
    {
        "type": 0,
        "location": [
            507,
            91
        ],
        "bgloc": [
            502,
            66
        ],
        "mean": [
            [
                82.93743908045977
            ]
        ],
        "min": [
            [
                9
            ]
        ],
        "max": [
            [
                249
            ]
        ],
        "RawIntDen": [
            [
                7215
            ]
        ],
        "IntDen": [
            [
                72.155572
            ]
        ],
        "local_bg": [
            [
                0.8275034482758621
            ]
        ],
        "area": [
            0.8700000000000002
        ],
        "distance": 50.56788481671424,
        "points": [
            [
                507.0,
                99.6
            ],
            [
                502.4,
                95.6
            ],
            [
                500.2,
                91.0
            ],
            [
                503.8,
                87.8
            ],
            [
                507.0,
                87.0
            ],
            [
                510.2,
                87.8
            ],
            [
                511.0,
                91.0
            ],
            [
                510.6,
                94.6
            ]
        ],
        "shift": null,
        "channel": 0,
        "closest_Dend": 0
    },
    {
        "type": 0,
        "location": [
            497,
            134
        ],
        "bgloc": [
            469,
            162
        ],
        "mean": [
            [
                10.10315625
            ]
        ],
        "min": [
            [
                2
            ]
        ],
        "max": [
            [
                29
            ]
        ],
        "RawIntDen": [
            [
                484
            ]
        ],
        "IntDen": [
            [
                4.849515000000001
            ]
        ],
        "local_bg": [
            [
                0.16665
            ]
        ],
        "area": [
            0.4800000000000001
        ],
        "distance": 51.62854498849406,
        "points": [
            [
                497.0,
                137.2
            ],
            [
                494.4,
                136.6
            ],
            [
                493.0,
                134.0
            ],
            [
                494.0,
                131.0
            ],
            [
                497.0,
                128.0
            ],
            [
                499.8,
                131.2
            ],
            [
                500.2,
                134.0
            ],
            [
                499.8,
                136.8
            ]
        ],
        "shift": null,
        "channel": 0,
        "closest_Dend": 0
    }
]